resticprofile/__init__.py
resticprofile/__main__.py
resticprofile/config.py
resticprofile/console.py
resticprofile/constants.py
resticprofile/context.py
resticprofile/error.py
resticprofile/filesearch.py
resticprofile/flag.py
resticprofile/groups.py
resticprofile/help.py
resticprofile/ionice.py
resticprofile/main.py
resticprofile/nice.py
resticprofile/profile.py
resticprofile/restic.py
resticprofile-0.5.2.dist-info/LICENSE
resticprofile-0.5.2.dist-info/METADATA
resticprofile-0.5.2.dist-info/WHEEL
resticprofile-0.5.2.dist-info/entry_points.txt
resticprofile-0.5.2.dist-info/top_level.txt
resticprofile-0.5.2.dist-info/RECORD
