Metadata-Version: 2.1
Name: resticprofile
Version: 0.5.2
Summary: Manage configuration profiles for restic backup
Home-page: https://github.com/creativeprojects/resticprofile
Author: Fred
Author-email: Fred@CreativeProjects.Tech
License: GPL-3.0-or-later
Keywords: restic backup configuration profiles
Platform: UNKNOWN
Classifier: Development Status :: 4 - Beta
Classifier: Environment :: Console
Classifier: License :: OSI Approved :: GNU General Public License v3 or later (GPLv3+)
Classifier: Natural Language :: English
Classifier: Topic :: System :: Archiving :: Backup
Classifier: Programming Language :: Python :: 3
Classifier: Operating System :: OS Independent
Requires-Python: >=3.5
Requires-Dist: setuptools
Requires-Dist: toml (<0.11,>=0.10)
Requires-Dist: colorama (<0.5,>=0.4)
